README.md
setup.py
cloudberry_netjson/__init__.py
cloudberry_netjson.egg-info/PKG-INFO
cloudberry_netjson.egg-info/SOURCES.txt
cloudberry_netjson.egg-info/dependency_links.txt
cloudberry_netjson.egg-info/requires.txt
cloudberry_netjson.egg-info/top_level.txt
cloudberry_openwisp/__init__.py