Metadata-Version: 1.0
Name: cloudberry-netjson
Version: 0.1
Summary: Cloudberry netjson extensions
Home-page: https://github.com/innovationgarage/cloudberry-netjson
Author: Egil Moeller
Author-email: egil@innovationgarage.no
License: UNKNOWN
Platform: UNKNOWN
